pycamv/__init__.py
pycamv/compare.py
pycamv/fragments.py
pycamv/gen_sequences.py
pycamv/mascot.py
pycamv/masses.py
pycamv/ms_labels.py
pycamv/proteowizard.py
pycamv/scans.py
pycamv/validate.py
pyproteome/__init__.py
pyproteome/analysis.py
pyproteome/bca.py
pyproteome/camv.py
pyproteome/data_sets.py
pyproteome/enrichment.py
pyproteome/fetch_data.py
pyproteome/levels.py
pyproteome/loading.py
pyproteome/logo.py
pyproteome/modification.py
pyproteome/motif.py
pyproteome/paths.py
pyproteome/protein.py
pyproteome/sequence.py
pyproteome/utils.py
pyproteome/version.py
pyproteome-0.1.0.dist-info/DESCRIPTION.rst
pyproteome-0.1.0.dist-info/METADATA
pyproteome-0.1.0.dist-info/RECORD
pyproteome-0.1.0.dist-info/WHEEL
pyproteome-0.1.0.dist-info/dependency_links.txt
pyproteome-0.1.0.dist-info/metadata.json
pyproteome-0.1.0.dist-info/top_level.txt
