Metadata-Version: 2.0
Name: pyproteome
Version: 0.1.0
Summary: Package for managing proteomics data
Home-page: https://github.com/naderm/pyproteome
Author: Nader Morshed
Author-email: morshed@mit.edu
License: BSD
Platform: UNKNOWN
Classifier: License :: OSI Approved :: BSD License
Classifier: Natural Language :: English
Classifier: Operating System :: OS Independent
Classifier: Programming Language :: Python :: 2
Classifier: Programming Language :: Python :: 2.7
Classifier: Programming Language :: Python :: 3
Classifier: Programming Language :: Python :: 3.3
Classifier: Programming Language :: Python :: 3.4
Classifier: Programming Language :: Python :: 3.5
Classifier: Topic :: Scientific/Engineering
Requires-Dist: adjustText
Requires-Dist: biopython (>=1.65)
Requires-Dist: fastcluster (>=1.1.20)
Requires-Dist: matplotlib (>=1.4.0)
Requires-Dist: matplotlib-venn (>=0.11)
Requires-Dist: networkx (>=1.9)
Requires-Dist: notebook (>=4.1.0)
Requires-Dist: numpy (>=1.9.0)
Requires-Dist: numpydoc (==0.6)
Requires-Dist: pandas (>=0.17.0)
Requires-Dist: pymzml (>=0.7.7)
Requires-Dist: scikit-learn (>=0.16.0)
Requires-Dist: scipy (>=0.16.0)
Requires-Dist: seaborn (>=0.6.0)
Requires-Dist: uniprot
Requires-Dist: xlsxwriter (>=0.8)
